bottle_oauthlib/__init__.py
bottle_oauthlib/oauth2.py
bottle_oauthlib-1.9.0.dist-info/LICENSE
bottle_oauthlib-1.9.0.dist-info/METADATA
bottle_oauthlib-1.9.0.dist-info/WHEEL
bottle_oauthlib-1.9.0.dist-info/top_level.txt
bottle_oauthlib-1.9.0.dist-info/RECORD
